{
    "poison": {
        "name": "poison",
        "description": "poisoned",
        "color": "green",
        "dps": [1],
        "duration": ["2d2"],
        "chance": [
            1.0
        ]
    },
    "paralyze": {
        "name": "paralyze",
        "paralyze": true,
        "description": "paralyzed",
        "color": "red",
        "duration": ["1d3", "1d4", "1d6"],
        "chance": [
            0.5,
            0.6,
            0.8
        ]
    },
    "disease": {
        "name": "disease",
        "description": "diseased",
        "color": "yellow",
        "drain_stats": [2, 4, 6],
        "duration": ["1d4", "1d6", "1d8"],
        "chance": [
            1.0
        ]
    },
    "bleed": {
        "name": "bleed",
        "description": "bleeding",
        "color": "light red",
        "delayed_damage": ["1d4"],
        "duration": ["1d4"],
        "chance": [
            1.0
        ]
    },
    "blind": {
        "name": "blind",
        "description": "blinded",
        "color": "yellow",
        "duration": ["1d4", "1d6", "1d8"],
        "hit_penalty": [25, 50, 75],
        "chance": [
            1.0
        ]
    },
    "strangle": {
        "name": "strangle",
        "description": "strangled",
        "duration": ["1d4", "1d6", "1d8"],
        "dps": [1, 2, 3],
        "slow": [0],
        "chance": [
            1.0
        ]
    },
    "slow": {
        "name": "slow",
        "description": "slowed",
        "slow": [0.8, 0.6, 0.4],
        "duration": ["1d4", "1d6", "1d8"],
        "chance": [
            1.0
        ]
    },
    "boost_ev": {
        "name": "boost EV",
        "description": "EV+",
        "power": [1.1, 1.2, 1.33]
    },
    "boost_ac": {
        "name": "boost AC",
        "description": "AC+",
        "power": [1.1, 1.2, 1.33]
    },
    "boost_hp": {
        "name": "boost HP",
        "description": "AC++",
        "power": [1.1, 1.2, 1.33]
    },
    "invisibility": {
        "name": "invisibility",
        "description": "invisible (sneak, EV+)",
        "color": "lighter blue",
        "duration": ["4d2", "5d2", "6d2"]
    },
    "sneak": {
        "name": "sneak",
        "description": "sneaking",
        "color": "lighter blue",
        "duration": [10, 20, 99]
    },
    "fly": {
        "name": "fly",
        "description": "flying (EV+)",
        "color": "lighter blue",
        "duration": [10, 15, 99],
        "power": [1.2, 1.33, 1.5]
    },
    "reveal": {
        "name": "reveal",
        "description": "revealing hidden tiles",
        "color": "amber",
        "duration": [10, 15, 99]
    },
    "heal": {
        "name": "heal",
        "description": "heal"
    },
    "summon": {
        "name": "summoning",
        "description": "summoning"
    }
}